proc_top.vhd
library IEEE;
use IEEE.STD_LOGIC_1164.ALL;
use IEEE.NUMERIC_STD.ALL;
use work.mytypes.all;

entity proc_top is
    Port (
        clk             : in STD_LOGIC;                 -- clk
        rst             : in STD_LOGIC;                 -- rst
        manual_toggle   : in STD_LOGIC;                 -- toggle to enter setup mode. also disables run mode
        run_toggle      : in STD_LOGIC;
        addr            : in STD_LOGIC_VECTOR(3 downto 0);     -- addr for manual data io 
        data_in         : in STD_LOGIC_VECTOR(7 downto 0);  -- d        Report "Memory " & result.g
        io_mode         : in STD_LOGIC;
        mem_toggle      : in STD_LOGIC
    );
end proc_top;

architecture Behavioral of proc_top is



    -- 4 bit registers
    signal MAR  : STD_LOGIC_VECTOR(3 downto 0) := "0000";
    signal PC   : STD_LOGIC_VECTOR(3 downto 0) := "0000";

    -- 8 bit registers
    signal IR   : STD_LOGIC_VECTOR(7 downto 0) := "00000000";
    signal ACC  : STD_LOGIC_VECTOR(7 downto 0) := "00000000";
    signal B    : STD_LOGIC_VECTOR(7 downto 0) := "00000000";
    -- define a memory type

    -- memory
    signal MEMORY : memory_type := (others => (others => '0'));

    -- 6 bit counter
--    signal counter : STD_LOGIC_VECTOR(5 downto 0) := "000000";



--    signal temp_PC : std_logic_vector(3 downto 0);

--    signal counter_reset : std_logic := '0';   
    signal reset_active : std_logic := '0';

    signal run_mode : std_logic := '0';

    procedure report_registers is
    begin
        Report "Registers - PC: [" & to_string(PC) & "]" &
        ", MAR: [" & to_string(MAR) & "]" &
        ", IR: [" & to_string(IR) & "]";

    end procedure report_registers;

    function getOp(op : std_logic_vector(3 downto 0)) return string is
    begin
        if op = "0000" then 
            return "LDA";
        elsif op = "0001" then
            return "ADD";
        elsif op = "0010" then
            return "SUB";
        elsif op = "1110" then
            return "OUT";
        elsif op = "1111" then
            return "HLT";
        else 
            return "???";
        end if;
    end function;

    function getOperand(op : std_logic_vector(3 downto 0); operand: std_logic_vector(3 downto 0)) return string is
    begin
        if op = "0000" or op = "0001" or op = "0010" then
            return to_hstring(operand) & "H";
        else 
            return "";
        end if;
    end function;
    

    procedure report_memory is
        variable opcode : std_logic_vector(3 downto 0);
        variable operand : std_logic_vector(3 downto 0);
        variable value : std_logic_vector(7 downto 0);
    begin
        for i in 0 to 15 loop
            value := MEMORY(i);
            opcode := value(7 downto 4);
            operand := value(3 downto 0);
            
            Report to_hstring(to_unsigned(i, 4)) & ":  " & to_hstring(value) & "  " & 
                getOp(opcode) & " " & getOperand(opcode, operand);
        end loop;
    end procedure;


begin

    -- initialize_ram_port : process
    -- begin
    --     ram_debug_out <= MEMORY;      
    --     wait;  
    -- end process;

    -- ring_counter_6bit : entity work.ring_counter_6bit
    -- port map
    --     (clk => clk, rst => counter_reset, count => counter);

    reset: process(rst, clk)
    begin
        Report "Reset Process - rst: " & to_string(rst) & ", run_mode: " 
            & to_string(run_mode) & ", reset active: " & to_string(reset_active);
        if rising_edge(clk) then
            if rst = '1' and reset_active = '0' then
 
                Report "Clearing Registers";
                -- clear all registers
  --              PC <= "0000";
                --MAR <= "0000";
                --IR <= "00000000"; 
                --ACC <= "00000000";
                --B <= "00000000";
                reset_active <= '1';
--                counter_reset <= '1';                
            elsif reset_active = '1' then
                reset_active <= '0';
--                counter_reset <= '0';
--                run_mode <= '1';
                Report "After Reset setting run mode to 1 - PC: " & to_string(PC) & ", IR: " & to_string(IR) & ", MAR: " & to_string(MAR);
            end if;
        end if;

    end process;

    normal_run_mode: 
    process(clk, rst, run_mode)
        variable temp_PC : std_logic_vector(3 downto 0) := "0000";
        variable temp_IR : std_logic_vector(7 downto 0) := "00000000";
        variable opcode : std_logic_vector(3 downto 0) := "0000";
        variable operand : std_logic_vector(3 downto 0) := "0000";
        variable stage : integer := 0;
    begin
         Report "Run Mode Clk process - stage: " & to_string(stage);
         report_registers;

        -- if rst = '1' then
        --     Report "Clearing Registers";
        --     -- clear all registers
        --     PC <= "0000";
        --     IR <= "00000000"; 
        --     ACC <= "00000000";
        --     MAR <= "0000";
        --     B <= "00000000";
--        elsif run_mode = '1' then 
        if run_mode = '1' and rst = '0' and rising_edge(clk) then 

            Report "Processing with PC: " & to_string(PC) & 
            ", temp_PC: " & to_string(temp_PC) &
        --    ", counter: " & to_string(counter) &
            ", Stage: " & to_string(stage) &
            ", IR: " & to_string(IR) &
            ", MAR: " & to_string(MAR) &
            ", OPCODE: " & to_string(opcode) &
            ", OPERAND: " & to_string(operand) &
            ", MEM[0]: " & to_string(MEMORY(0)) & 
            ", MEM[1]: " & to_string(MEMORY(1));
--                case counter is
            case stage is
--                    when "000001" => 
                when 0 => 
                                report "Stage 1 - Assigning PC to MAR";
                                MAR <= PC;
                                report "MAR after set from PC during stage 1. " & to_string(MAR);
--                    when "000010" => 
                when 1 => 
                                report "Stage 2 - Incrementing PC - current value of PC: " & to_string(PC);
                                temp_PC := STD_LOGIC_VECTOR(unsigned(PC) + 1);
                                PC <= temp_PC;
                                report "PC after increment during stage 2: " & to_string(temp_PC) & ", " & to_string(PC);
--                   when "000100" => 
                when 2 => 
                                report "Stage 3 - loading IR from memory - MAR: " & to_string(MAR) & ", MEM(0): " & to_string(MEMORY(to_integer(unsigned(MAR))));
                                temp_IR := MEMORY(to_integer(unsigned(MAR)));
                                IR <= temp_IR;
                                opcode := temp_IR(7 downto 4);
                                operand := temp_IR(3 downto 0);
                                report "IR after loading from memory during stage 3: temp_IR: " & to_string(temp_IR) & 
                                    ", opcode=" & to_string(opcode) & ", operand=" & to_string(operand);
                when others => null;

            end case;
            -- update stage
            stage := stage + 1;
            if stage >= 6 then
                stage := 0;
            end if;
        end if;
    end process;

    manual_toggle_process:
    process(manual_toggle)
    begin
        Report "Manual_Toggle_Process";
        if rising_edge(manual_toggle) then
            Report "Manual Toggle Process - setting run mode to 0";
  --          run_mode <= '0';
        end if;
    end process;

    run_toggle_process:
    process(run_toggle)
    begin
        Report "Run Toggle";
        if rising_edge(run_toggle) then
            Report "Run Toggle Process - setting run mode to 1";
            run_mode <= '1';
            report_memory;
        end if;
    end process;

    mem_toggle_process:
    process(run_mode, mem_toggle) 
    begin
        Report "mem_toggle Process" & ", run_mode: " & to_string(run_mode);
        if run_mode = '0' and rising_edge(mem_toggle) then
            Report "Handling Mem Toggle";
            if io_mode = '0' then   -- read mode
                Report "Reading Data from Memory";
        --          data <= MEMORY(to_integer(unsigned(addr)));
            elsif io_mode = '1' then   -- write mode
                Report "Writing Data " & format_reg_contents(data_in) & 
                    " to Memory [" & format_reg_contents(addr) & "]";
                MEMORY(to_integer(unsigned(addr))) <= data_in;
            end if;
        end if;
    end process;
end architecture;

proc_top_tb.vhd
library IEEE;
use IEEE.STD_LOGIC_1164.ALL;
use IEEE.NUMERIC_STD.ALL;
use work.mytypes.all;

entity proc_top_tb is
end proc_top_tb;

architecture Behavioral of proc_top_tb is
    signal clk :  STD_LOGIC := '0';
    signal rst : STD_LOGIC := '0';
--    signal run_mode : STD_LOGIC := '0';
    signal manual_toggle : STD_LOGIC := '0';
    signal io_mode : STD_LOGIC := '0';
    signal mem_toggle : STD_LOGIC := '0';
    signal run_toggle : STD_LOGIC := '0';
    signal addr : STD_LOGIC_VECTOR(3 downto 0);
    signal data_in : STD_LOGIC_VECTOR(7 downto 0);

    type mem_array_type is array (natural range <>) of std_logic_vector(7 downto 0);
    constant init_mem : mem_array_type := (
        b"00001001", b"00011010", b"00011011", b"00101100",
        b"11100000", b"11110000", b"10101010", b"10101010", 
        b"10101010", b"00010000", b"00010100", b"00011000",
        b"00100000", b"10101010", b"10101010", b"10101010");
begin

    proc : entity work.proc_top
    port map(
        clk => clk, 
        rst => rst, 
        manual_toggle => manual_toggle,
        run_toggle => run_toggle,
        addr => addr,
        data_in => data_in,
        io_mode => io_mode,
        mem_toggle => mem_toggle
    );

    clk_process :
    process
    begin
        clk <= '0';
        wait for 50 ns;
        clk <= '1';
        wait for 50 ns;
    end process;

    th:
        process
        begin

          --  run_mode <= '0';
            manual_toggle <= '1';
            io_mode <= '1';
            wait for 100 ns;

            Report "Loading Memory Contents";
            for i in init_mem'range loop

            -- manually set program in memory
                mem_toggle <= '0'; wait for 10 ns;
                addr <= std_logic_vector(to_unsigned(i, addr'length)); wait for 10 ns;
                data_in <= init_mem(i); wait for 10 ns;
                mem_toggle <= '1'; wait for 10 ns;
            end loop;

            Report "Finsihed Loading Memory";
            Report "Resetting";
            rst <= '1'; wait for 100 ns;
            
            rst <= '0';
            wait for 100 ns;
            run_toggle <= '1'; 

            -- Report "String Run Mode";
            -- run_mode <= '1';
            -- wait for 50 ns;

            wait;
        end process;
end Behavioral;

proc_top_tb.vcd
$date
  Mon Feb 19 20:21:43 2024
$end
$version
  GHDL v0
$end
$timescale
  1 fs
$end
$scope module standard $end
$upscope $end
$scope module textio $end
$upscope $end
$scope module std_logic_1164 $end
$upscope $end
$scope module numeric_std $end
$upscope $end
$scope module mytypes $end
$upscope $end
$scope module proc_top_tb $end
$var reg 1 ! clk $end
$var reg 1 " rst $end
$var reg 1 # manual_toggle $end
$var reg 1 $ io_mode $end
$var reg 1 % mem_toggle $end
$var reg 1 & run_toggle $end
$var reg 4 ' addr[3:0] $end
$var reg 8 ( data_in[7:0] $end
$scope module proc $end
$var reg 1 ) clk $end
$var reg 1 * rst $end
$var reg 1 + manual_toggle $end
$var reg 1 , run_toggle $end
$var reg 4 - addr[3:0] $end
$var reg 8 . data_in[7:0] $end
$var reg 1 / io_mode $end
$var reg 1 0 mem_toggle $end
$var reg 4 1 mar[3:0] $end
$var reg 4 2 pc[3:0] $end
$var reg 8 3 ir[7:0] $end
$var reg 8 4 acc[7:0] $end
$var reg 8 5 b[7:0] $end
$comment memory is not handled $end
$var reg 1 6 reset_active $end
$var reg 1 7 run_mode $end
$upscope $end
$upscope $end
$enddefinitions $end
#0
0!
0"
1#
1$
0%
0&
bUUUU '
bUUUUUUUU (
0)
0*
1+
0,
bUUUU -
bUUUUUUUU .
1/
00
b0000 1
b0000 2
b00000000 3
b00000000 4
b00000000 5
06
07
#50000000
1!
1)
#100000000
0!
0)
#110000000
b0000 '
b0000 -
#120000000
b00001001 (
b00001001 .
#130000000
1%
10
#140000000
0%
00
#150000000
1!
b0001 '
1)
b0001 -
#160000000
b00011010 (
b00011010 .
#170000000
1%
10
#180000000
0%
00
#190000000
b0010 '
b0010 -
#200000000
0!
b00011011 (
0)
b00011011 .
#210000000
1%
10
#220000000
0%
00
#230000000
b0011 '
b0011 -
#240000000
b00101100 (
b00101100 .
#250000000
1!
1%
1)
10
#260000000
0%
00
#270000000
b0100 '
b0100 -
#280000000
b11100000 (
b11100000 .
#290000000
1%
10
#300000000
0!
0%
0)
00
#310000000
b0101 '
b0101 -
#320000000
b11110000 (
b11110000 .
#330000000
1%
10
#340000000
0%
00
#350000000
1!
b0110 '
1)
b0110 -
#360000000
b10101010 (
b10101010 .
#370000000
1%
10
#380000000
0%
00
#390000000
b0111 '
b0111 -
#400000000
0!
0)
#410000000
1%
10
#420000000
0%
00
#430000000
b1000 '
b1000 -
#440000000
#450000000
1!
1%
1)
10
#460000000
0%
00
#470000000
b1001 '
b1001 -
#480000000
b00010000 (
b00010000 .
#490000000
1%
10
#500000000
0!
0%
0)
00
#510000000
b1010 '
b1010 -
#520000000
b00010100 (
b00010100 .
#530000000
1%
10
#540000000
0%
00
#550000000
1!
b1011 '
1)
b1011 -
#560000000
b00011000 (
b00011000 .
#570000000
1%
10
#580000000
0%
00
#590000000
b1100 '
b1100 -
#600000000
0!
b00100000 (
0)
b00100000 .
#610000000
1%
10
#620000000
0%
00
#630000000
b1101 '
b1101 -
#640000000
b10101010 (
b10101010 .
#650000000
1!
1%
1)
10
#660000000
0%
00
#670000000
b1110 '
b1110 -
#680000000
#690000000
1%
10
#700000000
0!
0%
0)
00
#710000000
b1111 '
b1111 -
#720000000
#730000000
1%
10
#740000000
1"
1*
#750000000
1!
1)
16
#800000000
0!
0)
#840000000
0"
0*
#850000000
1!
1)
06
#900000000
0!
0)
#940000000
1&
1,
17
#950000000
1!
1)
#1000000000
0!
0)
#1050000000
1!
1)
b0001 2
#1100000000
0!
0)
#1150000000
1!
1)
b00001001 3
#1200000000
0!
0)
#1250000000
1!
1)
#1300000000
0!
0)
#1350000000
1!
1)
#1400000000
0!
0)
#1450000000
1!
1)
#1500000000
0!
0)
#1550000000
1!
1)
b0001 1
#1600000000
0!
0)
#1650000000
1!
1)
b0010 2
#1700000000
0!
0)
#1750000000
1!
1)
b00011010 3
#1800000000
0!
0)
#1850000000
1!
1)
#1900000000
0!
0)
#1950000000
1!
1)
#2000000000
0!
0)
#2050000000
1!
1)
#2100000000
0!
0)
#2150000000
1!
1)
b0010 1
#2200000000
0!
0)
#2250000000
1!
1)
b0011 2
#2300000000
0!
0)
#2350000000
1!
1)
b00011011 3
#2400000000
0!
0)
#2450000000
1!
1)
#2500000000
0!
0)
#2550000000
1!
1)
#2600000000
0!
0)
#2650000000
1!
1)
#2700000000
0!
0)
#2750000000
1!
1)
b0011 1
#2800000000
0!
0)
#2850000000
1!
1)
b0100 2
#2900000000
0!
0)
#2950000000
1!
1)
b00101100 3
#3000000000
0!
0)
#3050000000
1!
1)
#3100000000
0!
0)
#3150000000
1!
1)
#3200000000
0!
0)
#3250000000
1!
1)
#3300000000
0!
0)
#3350000000
1!
1)
b0100 1
#3400000000
0!
0)
#3450000000
1!
1)
b0101 2
#3500000000
0!
0)
#3550000000
1!
1)
b11100000 3
#3600000000
0!
0)
#3650000000
1!
1)
#3700000000
0!
0)
#3750000000
1!
1)
#3800000000
0!
0)
#3850000000
1!
1)
#3900000000
0!
0)
#3950000000
1!
1)
b0101 1
#4000000000
0!
0)
#4050000000
1!
1)
b0110 2
#4100000000
0!
0)
#4150000000
1!
1)
b11110000 3
#4200000000
0!
0)
#4250000000
1!
1)
#4300000000
0!
0)
#4350000000
1!
1)
#4400000000
0!
0)
#4450000000
1!
1)
#4500000000
0!
0)
#4550000000
1!
1)
b0110 1
#4600000000
0!
0)
#4650000000
1!
1)
b0111 2
#4700000000
0!
0)
#4750000000
1!
1)
b10101010 3
#4800000000
0!
0)
#4850000000
1!
1)
#4900000000
0!
0)
#4950000000
1!
1)
#5000000000
0!
0)
#5050000000
1!
1)
#5100000000
0!
0)
#5150000000
1!
1)
b0111 1
#5200000000
0!
0)
#5250000000
1!
1)
b1000 2
#5300000000
0!
0)
#5350000000
1!
1)
#5400000000
0!
0)
#5450000000
1!
1)
#5500000000
0!
0)
#5550000000
1!
1)
#5600000000
0!
0)
#5650000000
1!
1)
#5700000000
0!
0)
#5750000000
1!
1)
b1000 1
#5800000000
0!
0)
#5850000000
1!
1)
b1001 2
#5900000000
0!
0)
#5950000000
1!
1)
#6000000000
0!
0)
#6050000000
1!
1)
#6100000000
0!
0)
#6150000000
1!
1)
#6200000000
0!
0)
#6250000000
1!
1)
#6300000000
0!
0)
#6350000000
1!
1)
b1001 1
#6400000000
0!
0)
#6450000000
1!
1)
b1010 2
#6500000000
0!
0)
#6550000000
1!
1)
b00010000 3
#6600000000
0!
0)
#6650000000
1!
1)
#6700000000
0!
0)
#6750000000
1!
1)
#6800000000
0!
0)
#6850000000
1!
1)
#6900000000
0!
0)
#6950000000
1!
1)
b1010 1
#7000000000
0!
0)
#7050000000
1!
1)
b1011 2
#7100000000
0!
0)
#7150000000
1!
1)
b00010100 3
#7200000000
0!
0)
#7250000000
1!
1)
#7300000000
0!
0)
#7350000000
1!
1)
#7400000000
0!
0)
#7450000000
1!
1)
#7500000000
0!
0)
#7550000000
1!
1)
b1011 1
#7600000000
0!
0)
#7650000000
1!
1)
b1100 2
#7700000000
0!
0)
#7750000000
1!
1)
b00011000 3
#7800000000
0!
0)
#7850000000
1!
1)
#7900000000
0!
0)
#7950000000
1!
1)
#8000000000
0!
0)
#8050000000
1!
1)
#8100000000
0!
0)
#8150000000
1!
1)
b1100 1
#8200000000
0!
0)
#8250000000
1!
1)
b1101 2
#8300000000
0!
0)
#8350000000
1!
1)
b00100000 3
#8400000000
0!
0)
#8450000000
1!
1)
#8500000000
0!
0)
#8550000000
1!
1)
#8600000000
0!
0)
#8650000000
1!
1)
#8700000000
0!
0)
#8750000000
1!
1)
b1101 1
#8800000000
0!
0)
#8850000000
1!
1)
b1110 2
#8900000000
0!
0)
#8950000000
1!
1)
b10101010 3
#9000000000
0!
0)
#9050000000
1!
1)
#9100000000
0!
0)
#9150000000
1!
1)
#9200000000
0!
0)
#9250000000
1!
1)
#9300000000
0!
0)
#9350000000
1!
1)
b1110 1
#9400000000
0!
0)
#9450000000
1!
1)
b1111 2
#9500000000
0!
0)
#9550000000
1!
1)
#9600000000
0!
0)
#9650000000
1!
1)
#9700000000
0!
0)
#9750000000
1!
1)
#9800000000
0!
0)
#9850000000
1!
1)
#9900000000
0!
0)
#9950000000
1!
1)
b1111 1
